MANIFEST.in
README.txt
setup.cfg
setup.py
docs/HISTORY.txt
docs/INSTALL.txt
docs/LICENSE.GPL
docs/LICENSE.txt
docs/changesetlinks.py
quills/__init__.py
quills.app.egg-info/PKG-INFO
quills.app.egg-info/SOURCES.txt
quills.app.egg-info/dependency_links.txt
quills.app.egg-info/entry_points.txt
quills.app.egg-info/namespace_packages.txt
quills.app.egg-info/not-zip-safe
quills.app.egg-info/requires.txt
quills.app.egg-info/top_level.txt
quills/app/__init__.py
quills/app/acquiringactions.py
quills/app/activation.py
quills/app/archive.py
quills/app/config.py
quills/app/configure.zcml
quills/app/contextstate.py
quills/app/interfaces.py
quills/app/locator.py
quills/app/rebuild_i18n.sh
quills/app/security.zcml
quills/app/setuphandlers.py
quills/app/syndication.py
quills/app/syndication.zcml
quills/app/tests.py
quills/app/topic.py
quills/app/traversal.py
quills/app/traversal.zcml
quills/app/utilities.py
quills/app/version.txt
quills/app/vice.py
quills/app/weblog.py
quills/app/weblogentrybrain.py
quills/app/browser/__init__.py
quills/app/browser/archive_view.pt
quills/app/browser/author_listing.pt
quills/app/browser/baseview.py
quills/app/browser/breadcrumbs.py
quills/app/browser/commentViews.py
quills/app/browser/configure.zcml
quills/app/browser/controllerView.py
quills/app/browser/defaultviews.py
quills/app/browser/discussionreply.py
quills/app/browser/macros.py
quills/app/browser/manage_comments.pt
quills/app/browser/quills_entry_macros.pt
quills/app/browser/quills_header_macros.pt
quills/app/browser/quills_weblog_macros.pt
quills/app/browser/topic_listing.pt
quills/app/browser/topic_view.pt
quills/app/browser/weblog_view.pt
quills/app/browser/weblogconfig.pt
quills/app/browser/weblogconfig.py
quills/app/browser/weblogentry_view.pt
quills/app/browser/weblogview.py
quills/app/locales/quills.app-manual.pot
quills/app/locales/quills.app.pot
quills/app/locales/cy/LC_MESSAGES/quills.app.po
quills/app/locales/da/LC_MESSAGES/quills.app.po
quills/app/locales/de/LC_MESSAGES/quills.app.po
quills/app/locales/en/LC_MESSAGES/quills.app.po
quills/app/locales/es/LC_MESSAGES/quills.app.po
quills/app/locales/eu/LC_MESSAGES/quills.app.po
quills/app/locales/fr/LC_MESSAGES/quills.app.po
quills/app/locales/it/LC_MESSAGES/quills.app.po
