Metadata-Version: 1.1
Name: quills.app
Version: 1.8.1
Summary: The Quills blogging suite. Contains code shared between Products.Quills and  Products.QuillsEnabled.
Home-page: http://plone.org/products/quills
Author: Quills Team
Author-email: plone-quills@googlegroups.com
License: GPL
Download-URL: http://svn.plone.org/svn/collective/quills.app
Keywords: plone blogging
Platform: UNKNOWN
Classifier: Development Status :: 5 - Production/Stable
Classifier: Framework :: Plone
Classifier: Framework :: Plone :: 3.2
Classifier: Framework :: Plone :: 3.3
Classifier: Framework :: Plone :: 4.0
Classifier: Framework :: Plone :: 4.1
Classifier: Framework :: Plone :: 4.2
Classifier: Framework :: Plone :: 4.3
Classifier: License :: OSI Approved :: GNU General Public License (GPL)
Classifier: Programming Language :: Python
Classifier: Topic :: Software Development :: Libraries :: Python Modules
